rupeshcalculator/__init__.py
rupeshcalculator-0.0.1.dist-info/METADATA
rupeshcalculator-0.0.1.dist-info/WHEEL
rupeshcalculator-0.0.1.dist-info/license.txt
rupeshcalculator-0.0.1.dist-info/top_level.txt
rupeshcalculator-0.0.1.dist-info/RECORD
